Workbook

Sheet Dashboard
A1: Monthly Sales Report — 2025
A2: Generated 2026-09-15 09:02 · source: raw transactions
A4: TOTAL REVENUE | C4: TOTAL PROFIT | E4: PROFIT MARGIN | G4: TOTAL ORDERS
A5: ='Monthly Summary'!B16 | C5: ='Monthly Summary'!D16 | E5: ='Monthly Summary'!H16 | G5: ='Monthly Summary'!F16
A6: UNITS SOLD | C6: AVG ORDER VALUE | E6: TOP REGION | G6: TOP PRODUCT
A7: ='Monthly Summary'!E16 | C7: ='Monthly Summary'!G16 | E7: =INDEX('Region Summary'!$A$4:$A$7,MATCH(MAX('Region Summary'!$B$4:$B$7),'Region Summary'!$B$4:$B$7,0)) | G7: =INDEX('Product Summary'!$A$4:$A$13,MATCH(MAX('Product Summary'!$C$4:$C$13),'Product Summary'!$C$4:$C$13,0))

Sheet Raw Data
A1: OrderID | B1: Date | C1: Month | D1: Region | E1: Country | F1: SalesRep | G1: Product | H1: Category | I1: Units | J1: UnitPrice | K1: Revenue | L1: Cost | M1: Profit
A2: SO-2025-05732 | B2: 45658 | C2: 2025-01 | D2: Europe | E2: France | F2: Oliver Smith | G2: Mechanical Keyboard | H2: Accessories | I2: 5 | J2: 104 | K2: 520 | L2: 310 | M2: 210
A3: SO-2025-01580 | B3: 45658 | C3: 2025-01 | D3: Europe | E3: Germany | F3: Oliver Smith | G3: CRM Suite (annual) | H3: Software | I3: 5 | J3: 882 | K3: 4410 | L3: 700 | M3: 3710
A4: SO-2025-05846 | B4: 45658 | C4: 2025-01 | D4: APAC | E4: Australia | F4: Priya Nair | G4: USB-C Dock | H4: Accessories | I4: 5 | J4: 156.6 | K4: 783 | L4: 440 | M4: 343
A5: SO-2025-05629 | B5: 45658 | C5: 2025-01 | D5: Europe | E5: France | F5: Emma Laurent | G5: Mechanical Keyboard | H5: Accessories | I5: 9 | J5: 123.5 | K5: 1111.5 | L5: 558 | M5: 553.5
A6: SO-2025-05498 | B6: 45658 | C6: 2025-01 | D6: Europe | E6: France | F6: Emma Laurent | G6: Mechanical Keyboard | H6: Accessories | I6: 6 | J6: 106.6 | K6: 639.6 | L6: 372 | M6: 267.6
A7: SO-2025-00750 | B7: 45658 | C7: 2025-01 | D7: Europe | E7: United Kingdom | F7: Noah Muller | G7: Wireless Mouse | H7: Accessories | I7: 2 | J7: 59.15 | K7: 118.3 | L7: 48 | M7: 70.3
A8: SO-2025-02434 | B8: 45658 | C8: 2025-01 | D8: Europe | E8: Spain | F8: Oliver Smith | G8: Wireless Mouse | H8: Accessories | I8: 1 | J8: 57.85 | K8: 57.85 | L8: 24 | M8: 33.85
A9: SO-2025-00791 | B9: 45658 | C9: 2025-01 | D9: APAC | E9: Japan | F9: Priya Nair | G9: Laptop Air 13 | H9: Hardware | I9: 1 | J9: 903 | K9: 903 | L9: 700 | M9: 203
A10: SO-2025-05385 | B10: 45658 | C10: 2025-01 | D10: Europe | E10: Spain | F10: Emma Laurent | G10: USB-C Dock | H10: Accessories | I10: 5 | J10: 171 | K10: 855 | L10: 440 | M10: 415
A11: SO-2025-02833 | B11: 45658 | C11: 2025-01 | D11: Europe | E11: Spain | F11: Noah Muller | G11: Analytics Add-on | H11: Software | I11: 24 | J11: 387 | K11: 9288 | L11: 1680 | M11: 7608
A12: SO-2025-01822 | B12: 45658 | C12: 2025-01 | D12: Europe | E12: Spain | F12: Oliver Smith | G12: Laptop Air 13 | H12: Hardware | I12: 2 | J12: 892.5 | K12: 1785 | L12: 1400 | M12: 385
A13: SO-2025-01379 | B13: 45658 | C13: 2025-01 | D13: Europe | E13: United Kingdom | F13: Emma Laurent | G13: Mechanical Keyboard | H13: Accessories | I13: 7 | J13: 128.7 | K13: 900.9 | L13: 434 | M13: 466.9
... A6001: SO-2025-04026 | B6001: 46022 | C6001: 2025-12 | D6001: Europe | E6001: United Kingdom | F6001: Noah Muller | G6001: Laptop Air 13 | H6001: Hardware | I6001: 3 | J6001: 945 | K6001: 2835 | L6001: 2100 | M6001: 735

Sheet Monthly Summary
A1: Monthly Sales Summary — 2025
A3: Month | B3: Revenue | C3: Cost | D3: Profit | E3: Units | F3: Orders | G3: Avg Order Value | H3: Profit Margin | I3: MoM Growth
A4: 2025-01 | B4: =SUMIFS('Raw Data'!$K$2:$K$6001,'Raw Data'!$C$2:$C$6001,$A4) | C4: =SUMIFS('Raw Data'!$L$2:$L$6001,'Raw Data'!$C$2:$C$6001,$A4) | D4: =B4-C4 | E4: =SUMIFS('Raw Data'!$I$2:$I$6001,'Raw Data'!$C$2:$C$6001,$A4) | F4: =COUNTIF('Raw Data'!$C$2:$C$6001,$A4) | G4: =IFERROR(B4/F4,0) | H4: =IFERROR(D4/B4,0)
A5: 2025-02 | B5: =SUMIFS('Raw Data'!$K$2:$K$6001,'Raw Data'!$C$2:$C$6001,$A5) | C5: =SUMIFS('Raw Data'!$L$2:$L$6001,'Raw Data'!$C$2:$C$6001,$A5) | D5: =B5-C5 | E5: =SUMIFS('Raw Data'!$I$2:$I$6001,'Raw Data'!$C$2:$C$6001,$A5) | F5: =COUNTIF('Raw Data'!$C$2:$C$6001,$A5) | G5: =IFERROR(B5/F5,0) | H5: =IFERROR(D5/B5,0) | I5: =IFERROR(B5/B4-1,"")
A6: 2025-03 | B6: =SUMIFS('Raw Data'!$K$2:$K$6001,'Raw Data'!$C$2:$C$6001,$A6) | C6: =SUMIFS('Raw Data'!$L$2:$L$6001,'Raw Data'!$C$2:$C$6001,$A6) | D6: =B6-C6 | E6: =SUMIFS('Raw Data'!$I$2:$I$6001,'Raw Data'!$C$2:$C$6001,$A6) | F6: =COUNTIF('Raw Data'!$C$2:$C$6001,$A6) | G6: =IFERROR(B6/F6,0) | H6: =IFERROR(D6/B6,0) | I6: =IFERROR(B6/B5-1,"")
A7: 2025-04 | B7: =SUMIFS('Raw Data'!$K$2:$K$6001,'Raw Data'!$C$2:$C$6001,$A7) | C7: =SUMIFS('Raw Data'!$L$2:$L$6001,'Raw Data'!$C$2:$C$6001,$A7) | D7: =B7-C7 | E7: =SUMIFS('Raw Data'!$I$2:$I$6001,'Raw Data'!$C$2:$C$6001,$A7) | F7: =COUNTIF('Raw Data'!$C$2:$C$6001,$A7) | G7: =IFERROR(B7/F7,0) | H7: =IFERROR(D7/B7,0) | I7: =IFERROR(B7/B6-1,"")
A8: 2025-05 | B8: =SUMIFS('Raw Data'!$K$2:$K$6001,'Raw Data'!$C$2:$C$6001,$A8) | C8: =SUMIFS('Raw Data'!$L$2:$L$6001,'Raw Data'!$C$2:$C$6001,$A8) | D8: =B8-C8 | E8: =SUMIFS('Raw Data'!$I$2:$I$6001,'Raw Data'!$C$2:$C$6001,$A8) | F8: =COUNTIF('Raw Data'!$C$2:$C$6001,$A8) | G8: =IFERROR(B8/F8,0) | H8: =IFERROR(D8/B8,0) | I8: =IFERROR(B8/B7-1,"")
A9: 2025-06 | B9: =SUMIFS('Raw Data'!$K$2:$K$6001,'Raw Data'!$C$2:$C$6001,$A9) | C9: =SUMIFS('Raw Data'!$L$2:$L$6001,'Raw Data'!$C$2:$C$6001,$A9) | D9: =B9-C9 | E9: =SUMIFS('Raw Data'!$I$2:$I$6001,'Raw Data'!$C$2:$C$6001,$A9) | F9: =COUNTIF('Raw Data'!$C$2:$C$6001,$A9) | G9: =IFERROR(B9/F9,0) | H9: =IFERROR(D9/B9,0) | I9: =IFERROR(B9/B8-1,"")
A10: 2025-07 | B10: =SUMIFS('Raw Data'!$K$2:$K$6001,'Raw Data'!$C$2:$C$6001,$A10) | C10: =SUMIFS('Raw Data'!$L$2:$L$6001,'Raw Data'!$C$2:$C$6001,$A10) | D10: =B10-C10 | E10: =SUMIFS('Raw Data'!$I$2:$I$6001,'Raw Data'!$C$2:$C$6001,$A10) | F10: =COUNTIF('Raw Data'!$C$2:$C$6001,$A10) | G10: =IFERROR(B10/F10,0) | H10: =IFERROR(D10/B10,0) | I10: =IFERROR(B10/B9-1,"")
A11: 2025-08 | B11: =SUMIFS('Raw Data'!$K$2:$K$6001,'Raw Data'!$C$2:$C$6001,$A11) | C11: =SUMIFS('Raw Data'!$L$2:$L$6001,'Raw Data'!$C$2:$C$6001,$A11) | D11: =B11-C11 | E11: =SUMIFS('Raw Data'!$I$2:$I$6001,'Raw Data'!$C$2:$C$6001,$A11) | F11: =COUNTIF('Raw Data'!$C$2:$C$6001,$A11) | G11: =IFERROR(B11/F11,0) | H11: =IFERROR(D11/B11,0) | I11: =IFERROR(B11/B10-1,"")
A12: 2025-09 | B12: =SUMIFS('Raw Data'!$K$2:$K$6001,'Raw Data'!$C$2:$C$6001,$A12) | C12: =SUMIFS('Raw Data'!$L$2:$L$6001,'Raw Data'!$C$2:$C$6001,$A12) | D12: =B12-C12 | E12: =SUMIFS('Raw Data'!$I$2:$I$6001,'Raw Data'!$C$2:$C$6001,$A12) | F12: =COUNTIF('Raw Data'!$C$2:$C$6001,$A12) | G12: =IFERROR(B12/F12,0) | H12: =IFERROR(D12/B12,0) | I12: =IFERROR(B12/B11-1,"")
A13: 2025-10 | B13: =SUMIFS('Raw Data'!$K$2:$K$6001,'Raw Data'!$C$2:$C$6001,$A13) | C13: =SUMIFS('Raw Data'!$L$2:$L$6001,'Raw Data'!$C$2:$C$6001,$A13) | D13: =B13-C13 | E13: =SUMIFS('Raw Data'!$I$2:$I$6001,'Raw Data'!$C$2:$C$6001,$A13) | F13: =COUNTIF('Raw Data'!$C$2:$C$6001,$A13) | G13: =IFERROR(B13/F13,0) | H13: =IFERROR(D13/B13,0) | I13: =IFERROR(B13/B12-1,"")
A14: 2025-11 | B14: =SUMIFS('Raw Data'!$K$2:$K$6001,'Raw Data'!$C$2:$C$6001,$A14) | C14: =SUMIFS('Raw Data'!$L$2:$L$6001,'Raw Data'!$C$2:$C$6001,$A14) | D14: =B14-C14 | E14: =SUMIFS('Raw Data'!$I$2:$I$6001,'Raw Data'!$C$2:$C$6001,$A14) | F14: =COUNTIF('Raw Data'!$C$2:$C$6001,$A14) | G14: =IFERROR(B14/F14,0) | H14: =IFERROR(D14/B14,0) | I14: =IFERROR(B14/B13-1,"")
A15: 2025-12 | B15: =SUMIFS('Raw Data'!$K$2:$K$6001,'Raw Data'!$C$2:$C$6001,$A15) | C15: =SUMIFS('Raw Data'!$L$2:$L$6001,'Raw Data'!$C$2:$C$6001,$A15) | D15: =B15-C15 | E15: =SUMIFS('Raw Data'!$I$2:$I$6001,'Raw Data'!$C$2:$C$6001,$A15) | F15: =COUNTIF('Raw Data'!$C$2:$C$6001,$A15) | G15: =IFERROR(B15/F15,0) | H15: =IFERROR(D15/B15,0) | I15: =IFERROR(B15/B14-1,"")
A16: TOTAL | B16: =SUM(B4:B15) | C16: =SUM(C4:C15) | D16: =B16-C16 | E16: =SUM(E4:E15) | F16: =SUM(F4:F15) | G16: =IFERROR(B16/F16,0) | H16: =IFERROR(D16/B16,0)

Sheet Region Summary
A1: Revenue by Region
A3: Region | B3: Revenue | C3: Cost | D3: Profit | E3: Units | F3: Orders | G3: Profit Margin | H3: Share of Total
A4: APAC | B4: =SUMIFS('Raw Data'!$K$2:$K$6001,'Raw Data'!$D$2:$D$6001,$A4) | C4: =SUMIFS('Raw Data'!$L$2:$L$6001,'Raw Data'!$D$2:$D$6001,$A4) | D4: =B4-C4 | E4: =SUMIFS('Raw Data'!$I$2:$I$6001,'Raw Data'!$D$2:$D$6001,$A4) | F4: =COUNTIF('Raw Data'!$D$2:$D$6001,$A4) | G4: =IFERROR(D4/B4,0) | H4: =IFERROR(B4/$B$8,0)
A5: Europe | B5: =SUMIFS('Raw Data'!$K$2:$K$6001,'Raw Data'!$D$2:$D$6001,$A5) | C5: =SUMIFS('Raw Data'!$L$2:$L$6001,'Raw Data'!$D$2:$D$6001,$A5) | D5: =B5-C5 | E5: =SUMIFS('Raw Data'!$I$2:$I$6001,'Raw Data'!$D$2:$D$6001,$A5) | F5: =COUNTIF('Raw Data'!$D$2:$D$6001,$A5) | G5: =IFERROR(D5/B5,0) | H5: =IFERROR(B5/$B$8,0)
A6: LATAM | B6: =SUMIFS('Raw Data'!$K$2:$K$6001,'Raw Data'!$D$2:$D$6001,$A6) | C6: =SUMIFS('Raw Data'!$L$2:$L$6001,'Raw Data'!$D$2:$D$6001,$A6) | D6: =B6-C6 | E6: =SUMIFS('Raw Data'!$I$2:$I$6001,'Raw Data'!$D$2:$D$6001,$A6) | F6: =COUNTIF('Raw Data'!$D$2:$D$6001,$A6) | G6: =IFERROR(D6/B6,0) | H6: =IFERROR(B6/$B$8,0)
A7: North America | B7: =SUMIFS('Raw Data'!$K$2:$K$6001,'Raw Data'!$D$2:$D$6001,$A7) | C7: =SUMIFS('Raw Data'!$L$2:$L$6001,'Raw Data'!$D$2:$D$6001,$A7) | D7: =B7-C7 | E7: =SUMIFS('Raw Data'!$I$2:$I$6001,'Raw Data'!$D$2:$D$6001,$A7) | F7: =COUNTIF('Raw Data'!$D$2:$D$6001,$A7) | G7: =IFERROR(D7/B7,0) | H7: =IFERROR(B7/$B$8,0)
A8: TOTAL | B8: =SUM(B4:B7) | C8: =SUM(C4:C7) | D8: =B8-C8 | E8: =SUM(E4:E7) | F8: =SUM(F4:F7) | G8: =IFERROR(D8/B8,0)

Sheet Product Summary
A1: Revenue by Product
A3: Product | B3: Category | C3: Revenue | D3: Cost | E3: Profit | F3: Units | G3: Profit Margin | H3: Share of Total
A4: CRM Suite (annual) | B4: Software | C4: =SUMIFS('Raw Data'!$K$2:$K$6001,'Raw Data'!$G$2:$G$6001,$A4) | D4: =SUMIFS('Raw Data'!$L$2:$L$6001,'Raw Data'!$G$2:$G$6001,$A4) | E4: =C4-D4 | F4: =SUMIFS('Raw Data'!$I$2:$I$6001,'Raw Data'!$G$2:$G$6001,$A4) | G4: =IFERROR(E4/C4,0) | H4: =IFERROR(C4/$C$14,0)
A5: Security Suite | B5: Software | C5: =SUMIFS('Raw Data'!$K$2:$K$6001,'Raw Data'!$G$2:$G$6001,$A5) | D5: =SUMIFS('Raw Data'!$L$2:$L$6001,'Raw Data'!$G$2:$G$6001,$A5) | E5: =C5-D5 | F5: =SUMIFS('Raw Data'!$I$2:$I$6001,'Raw Data'!$G$2:$G$6001,$A5) | G5: =IFERROR(E5/C5,0) | H5: =IFERROR(C5/$C$14,0)
A6: Analytics Add-on | B6: Software | C6: =SUMIFS('Raw Data'!$K$2:$K$6001,'Raw Data'!$G$2:$G$6001,$A6) | D6: =SUMIFS('Raw Data'!$L$2:$L$6001,'Raw Data'!$G$2:$G$6001,$A6) | E6: =C6-D6 | F6: =SUMIFS('Raw Data'!$I$2:$I$6001,'Raw Data'!$G$2:$G$6001,$A6) | G6: =IFERROR(E6/C6,0) | H6: =IFERROR(C6/$C$14,0)
A7: Laptop Pro 15 | B7: Hardware | C7: =SUMIFS('Raw Data'!$K$2:$K$6001,'Raw Data'!$G$2:$G$6001,$A7) | D7: =SUMIFS('Raw Data'!$L$2:$L$6001,'Raw Data'!$G$2:$G$6001,$A7) | E7: =C7-D7 | F7: =SUMIFS('Raw Data'!$I$2:$I$6001,'Raw Data'!$G$2:$G$6001,$A7) | G7: =IFERROR(E7/C7,0) | H7: =IFERROR(C7/$C$14,0)
A8: Laptop Air 13 | B8: Hardware | C8: =SUMIFS('Raw Data'!$K$2:$K$6001,'Raw Data'!$G$2:$G$6001,$A8) | D8: =SUMIFS('Raw Data'!$L$2:$L$6001,'Raw Data'!$G$2:$G$6001,$A8) | E8: =C8-D8 | F8: =SUMIFS('Raw Data'!$I$2:$I$6001,'Raw Data'!$G$2:$G$6001,$A8) | G8: =IFERROR(E8/C8,0) | H8: =IFERROR(C8/$C$14,0)
A9: UltraWide Monitor 34 | B9: Hardware | C9: =SUMIFS('Raw Data'!$K$2:$K$6001,'Raw Data'!$G$2:$G$6001,$A9) | D9: =SUMIFS('Raw Data'!$L$2:$L$6001,'Raw Data'!$G$2:$G$6001,$A9) | E9: =C9-D9 | F9: =SUMIFS('Raw Data'!$I$2:$I$6001,'Raw Data'!$G$2:$G$6001,$A9) | G9: =IFERROR(E9/C9,0) | H9: =IFERROR(C9/$C$14,0)
A10: Noise-Cancel Headset | B10: Accessories | C10: =SUMIFS('Raw Data'!$K$2:$K$6001,'Raw Data'!$G$2:$G$6001,$A10) | D10: =SUMIFS('Raw Data'!$L$2:$L$6001,'Raw Data'!$G$2:$G$6001,$A10) | E10: =C10-D10 | F10: =SUMIFS('Raw Data'!$I$2:$I$6001,'Raw Data'!$G$2:$G$6001,$A10) | G10: =IFERROR(E10/C10,0) | H10: =IFERROR(C10/$C$14,0)
A11: USB-C Dock | B11: Accessories | C11: =SUMIFS('Raw Data'!$K$2:$K$6001,'Raw Data'!$G$2:$G$6001,$A11) | D11: =SUMIFS('Raw Data'!$L$2:$L$6001,'Raw Data'!$G$2:$G$6001,$A11) | E11: =C11-D11 | F11: =SUMIFS('Raw Data'!$I$2:$I$6001,'Raw Data'!$G$2:$G$6001,$A11) | G11: =IFERROR(E11/C11,0) | H11: =IFERROR(C11/$C$14,0)
A12: Mechanical Keyboard | B12: Accessories | C12: =SUMIFS('Raw Data'!$K$2:$K$6001,'Raw Data'!$G$2:$G$6001,$A12) | D12: =SUMIFS('Raw Data'!$L$2:$L$6001,'Raw Data'!$G$2:$G$6001,$A12) | E12: =C12-D12 | F12: =SUMIFS('Raw Data'!$I$2:$I$6001,'Raw Data'!$G$2:$G$6001,$A12) | G12: =IFERROR(E12/C12,0) | H12: =IFERROR(C12/$C$14,0)
A13: Wireless Mouse | B13: Accessories | C13: =SUMIFS('Raw Data'!$K$2:$K$6001,'Raw Data'!$G$2:$G$6001,$A13) | D13: =SUMIFS('Raw Data'!$L$2:$L$6001,'Raw Data'!$G$2:$G$6001,$A13) | E13: =C13-D13 | F13: =SUMIFS('Raw Data'!$I$2:$I$6001,'Raw Data'!$G$2:$G$6001,$A13) | G13: =IFERROR(E13/C13,0) | H13: =IFERROR(C13/$C$14,0)
A14: TOTAL | C14: =SUM(C4:C13) | D14: =SUM(D4:D13) | E14: =C14-D14 | F14: =SUM(F4:F13) | G14: =IFERROR(E14/C14,0)

Sheet Rep Performance
A1: Sales Rep Performance
A3: Sales Rep | B3: Region | C3: Revenue | D3: Orders | E3: Avg Deal Size | F3: Target | G3: Attainment | H3: Rank
A4: Ava Thompson | B4: North America | C4: =SUMIFS('Raw Data'!$K$2:$K$6001,'Raw Data'!$F$2:$F$6001,$A4) | D4: =COUNTIF('Raw Data'!$F$2:$F$6001,$A4) | E4: =IFERROR(C4/D4,0) | F4: 1667000 | G4: =IFERROR(C4/F4,0) | H4: =RANK(C4,$C$4:$C$15)
A5: Liam Chen | B5: North America | C5: =SUMIFS('Raw Data'!$K$2:$K$6001,'Raw Data'!$F$2:$F$6001,$A5) | D5: =COUNTIF('Raw Data'!$F$2:$F$6001,$A5) | E5: =IFERROR(C5/D5,0) | F5: 1667000 | G5: =IFERROR(C5/F5,0) | H5: =RANK(C5,$C$4:$C$15)
A6: Sofia Ramirez | B6: North America | C6: =SUMIFS('Raw Data'!$K$2:$K$6001,'Raw Data'!$F$2:$F$6001,$A6) | D6: =COUNTIF('Raw Data'!$F$2:$F$6001,$A6) | E6: =IFERROR(C6/D6,0) | F6: 1667000 | G6: =IFERROR(C6/F6,0) | H6: =RANK(C6,$C$4:$C$15)
A7: Noah Muller | B7: Europe | C7: =SUMIFS('Raw Data'!$K$2:$K$6001,'Raw Data'!$F$2:$F$6001,$A7) | D7: =COUNTIF('Raw Data'!$F$2:$F$6001,$A7) | E7: =IFERROR(C7/D7,0) | F7: 1667000 | G7: =IFERROR(C7/F7,0) | H7: =RANK(C7,$C$4:$C$15)
A8: Oliver Smith | B8: Europe | C8: =SUMIFS('Raw Data'!$K$2:$K$6001,'Raw Data'!$F$2:$F$6001,$A8) | D8: =COUNTIF('Raw Data'!$F$2:$F$6001,$A8) | E8: =IFERROR(C8/D8,0) | F8: 1667000 | G8: =IFERROR(C8/F8,0) | H8: =RANK(C8,$C$4:$C$15)
A9: Emma Laurent | B9: Europe | C9: =SUMIFS('Raw Data'!$K$2:$K$6001,'Raw Data'!$F$2:$F$6001,$A9) | D9: =COUNTIF('Raw Data'!$F$2:$F$6001,$A9) | E9: =IFERROR(C9/D9,0) | F9: 1667000 | G9: =IFERROR(C9/F9,0) | H9: =RANK(C9,$C$4:$C$15)
A10: Haruto Sato | B10: APAC | C10: =SUMIFS('Raw Data'!$K$2:$K$6001,'Raw Data'!$F$2:$F$6001,$A10) | D10: =COUNTIF('Raw Data'!$F$2:$F$6001,$A10) | E10: =IFERROR(C10/D10,0) | F10: 1667000 | G10: =IFERROR(C10/F10,0) | H10: =RANK(C10,$C$4:$C$15)
A11: Priya Nair | B11: APAC | C11: =SUMIFS('Raw Data'!$K$2:$K$6001,'Raw Data'!$F$2:$F$6001,$A11) | D11: =COUNTIF('Raw Data'!$F$2:$F$6001,$A11) | E11: =IFERROR(C11/D11,0) | F11: 1667000 | G11: =IFERROR(C11/F11,0) | H11: =RANK(C11,$C$4:$C$15)
A12: Chloe Wong | B12: APAC | C12: =SUMIFS('Raw Data'!$K$2:$K$6001,'Raw Data'!$F$2:$F$6001,$A12) | D12: =COUNTIF('Raw Data'!$F$2:$F$6001,$A12) | E12: =IFERROR(C12/D12,0) | F12: 1667000 | G12: =IFERROR(C12/F12,0) | H12: =RANK(C12,$C$4:$C$15)
A13: Mateo Silva | B13: LATAM | C13: =SUMIFS('Raw Data'!$K$2:$K$6001,'Raw Data'!$F$2:$F$6001,$A13) | D13: =COUNTIF('Raw Data'!$F$2:$F$6001,$A13) | E13: =IFERROR(C13/D13,0) | F13: 1667000 | G13: =IFERROR(C13/F13,0) | H13: =RANK(C13,$C$4:$C$15)
A14: Diego Fernandez | B14: LATAM | C14: =SUMIFS('Raw Data'!$K$2:$K$6001,'Raw Data'!$F$2:$F$6001,$A14) | D14: =COUNTIF('Raw Data'!$F$2:$F$6001,$A14) | E14: =IFERROR(C14/D14,0) | F14: 1667000 | G14: =IFERROR(C14/F14,0) | H14: =RANK(C14,$C$4:$C$15)
A15: Camila Rojas | B15: LATAM | C15: =SUMIFS('Raw Data'!$K$2:$K$6001,'Raw Data'!$F$2:$F$6001,$A15) | D15: =COUNTIF('Raw Data'!$F$2:$F$6001,$A15) | E15: =IFERROR(C15/D15,0) | F15: 1667000 | G15: =IFERROR(C15/F15,0) | H15: =RANK(C15,$C$4:$C$15)

Sheet Category Summary
A1: Revenue by Category
A3: Category | B3: Revenue | C3: Cost | D3: Profit | E3: Units | F3: Orders | G3: Profit Margin | H3: Share of Total
A4: Software | B4: =SUMIFS('Raw Data'!$K$2:$K$6001,'Raw Data'!$H$2:$H$6001,$A4) | C4: =SUMIFS('Raw Data'!$L$2:$L$6001,'Raw Data'!$H$2:$H$6001,$A4) | D4: =B4-C4 | E4: =SUMIFS('Raw Data'!$I$2:$I$6001,'Raw Data'!$H$2:$H$6001,$A4) | F4: =COUNTIF('Raw Data'!$H$2:$H$6001,$A4) | G4: =IFERROR(D4/B4,0) | H4: =IFERROR(B4/$B$7,0)
A5: Hardware | B5: =SUMIFS('Raw Data'!$K$2:$K$6001,'Raw Data'!$H$2:$H$6001,$A5) | C5: =SUMIFS('Raw Data'!$L$2:$L$6001,'Raw Data'!$H$2:$H$6001,$A5) | D5: =B5-C5 | E5: =SUMIFS('Raw Data'!$I$2:$I$6001,'Raw Data'!$H$2:$H$6001,$A5) | F5: =COUNTIF('Raw Data'!$H$2:$H$6001,$A5) | G5: =IFERROR(D5/B5,0) | H5: =IFERROR(B5/$B$7,0)
A6: Accessories | B6: =SUMIFS('Raw Data'!$K$2:$K$6001,'Raw Data'!$H$2:$H$6001,$A6) | C6: =SUMIFS('Raw Data'!$L$2:$L$6001,'Raw Data'!$H$2:$H$6001,$A6) | D6: =B6-C6 | E6: =SUMIFS('Raw Data'!$I$2:$I$6001,'Raw Data'!$H$2:$H$6001,$A6) | F6: =COUNTIF('Raw Data'!$H$2:$H$6001,$A6) | G6: =IFERROR(D6/B6,0) | H6: =IFERROR(B6/$B$7,0)
A7: TOTAL | B7: =SUM(B4:B6) | C7: =SUM(C4:C6) | D7: =B7-C7 | E7: =SUM(E4:E6) | F7: =SUM(F4:F6) | G7: =IFERROR(D7/B7,0)
